manim_smart_algebra/__init__.py
manim_smart_algebra/actions/__init__.py
manim_smart_algebra/actions/action_core.py
manim_smart_algebra/actions/animations.py
manim_smart_algebra/actions/combinations.py
manim_smart_algebra/actions/common.py
manim_smart_algebra/actions/variants.py
manim_smart_algebra/expressions/__init__.py
manim_smart_algebra/expressions/common.py
manim_smart_algebra/expressions/expression_core.py
manim_smart_algebra/expressions/functions.py
manim_smart_algebra/expressions/numbers.py
manim_smart_algebra/expressions/operations.py
manim_smart_algebra/expressions/relations.py
manim_smart_algebra/expressions/sequences.py
manim_smart_algebra/expressions/variables.py
manim_smart_algebra/extra/calculus/calculus_core.py
manim_smart_algebra/extra/calculus/common.py
manim_smart_algebra/extra/trigonometry/common.py
manim_smart_algebra/extra/trigonometry/trigonometry_core.py
manim_smart_algebra/unifier/vstack.py
manim_smart_algebra/unifier/zipper.py
manim_smart_algebra/utils.py
manim_smart_algebra-0.4.2.dist-info/METADATA
manim_smart_algebra-0.4.2.dist-info/WHEEL
manim_smart_algebra-0.4.2.dist-info/RECORD
