Metadata-Version: 2.3
Name: manim-smart-algebra
Version: 0.4.2
Summary: Manim plugin which aims to make it much easier to meaningfully transform algebra expressions.
License: None
Author: John Connell
Author-email: johnconnelltutor@gmail.com
Requires-Python: >=3.8
Classifier: License :: Other/Proprietary License
Classifier: Programming Language :: Python :: 3
Classifier: Programming Language :: Python :: 3.8
Classifier: Programming Language :: Python :: 3.9
Classifier: Programming Language :: Python :: 3.10
Classifier: Programming Language :: Python :: 3.11
Classifier: Programming Language :: Python :: 3.12
Classifier: Programming Language :: Python :: 3.13
Provides-Extra: manimce
Provides-Extra: manimgl
Requires-Dist: MF_Tools (>=1.3.1)
Requires-Dist: manim (>=0.17.0) ; extra == "manimce"
Requires-Dist: manimgl (>=1.7.0) ; extra == "manimgl"
Project-URL: Repository, https://github.com/TheMathematicFanatic/manim_smart_algebra
